{
    "Apple": {
        "type_id": "sku_id0",
        "unit_cost": 13,
        "holding_cost": 6,
        "temp_requirements": 0,
        "target_level": 10
    },
    "Banana": {
        "type_id": "sku_id1",
        "unit_cost": 7,
        "holding_cost": 6,
        "temp_requirements": 25,
        "target_level": 10
    },
    "Chicken": {
        "type_id": "sku_id2",
        "unit_cost": 14,
        "holding_cost": 1,
        "temp_requirements": 5,
        "target_level": 10
    },
    "Beef": {
        "type_id": "sku_id3",
        "unit_cost": 6,
        "holding_cost": 8,
        "temp_requirements": 5,
        "target_level": 10
    },
    "Pork": {
        "type_id": "sku_id4",
        "unit_cost": 1,
        "holding_cost": 11,
        "temp_requirements": 5,
        "target_level": 10
    },
    "Garlic": {
        "type_id": "sku_id5",
        "unit_cost": 2,
        "holding_cost": 3,
        "temp_requirements": 5,
        "target_level": 100
    },
    "Mushrooms": {
        "type_id": "sku_id6",
        "unit_cost": 7,
        "holding_cost": 11,
        "temp_requirements": 5,
        "target_level": 10
    },
    "Pear": {
        "type_id": "sku_id7",
        "unit_cost": 12,
        "holding_cost": 3,
        "temp_requirements": 0,
        "target_level": 10
    },
    "Potatoes": {
        "type_id": "sku_id8",
        "unit_cost": 3,
        "holding_cost": 9,
        "temp_requirements": 0,
        "target_level": 50
    },
    "Cabbage": {
        "type_id": "sku_id9",
        "unit_cost": 10,
        "holding_cost": 10,
        "temp_requirements": 0,
        "target_level": 10
    },
    "Carrot": {
        "type_id": "sku_id10",
        "unit_cost": 7,
        "holding_cost": 3,
        "temp_requirements": 5,
        "target_level": 10
    }
}